Metadata-Version: 1.1
Name: winevt
Version: 0.0.11
Summary: Script to programmatically interface with Windows Events.
Home-page: https://github.com/owlz/winevt
Author: Michael Bann
Author-email: self@bannsecurity.com
License: MIT
Keywords: windows event evt evtx
Platform: UNKNOWN
Classifier: Development Status :: 5 - Production/Stable
Classifier: Intended Audience :: End Users/Desktop
Classifier: License :: OSI Approved :: MIT License
Classifier: Programming Language :: Python :: 3
Classifier: Operating System :: Microsoft :: Windows
Classifier: Environment :: Console
